ckanapi/__init__.py
ckanapi/common.py
ckanapi/datapackage.py
ckanapi/errors.py
ckanapi/localckan.py
ckanapi/remoteckan.py
ckanapi/testappckan.py
ckanapi/version.py
ckanapi/cli/__init__.py
ckanapi/cli/action.py
ckanapi/cli/batch.py
ckanapi/cli/ckan_click.py
ckanapi/cli/delete.py
ckanapi/cli/dump.py
ckanapi/cli/load.py
ckanapi/cli/main.py
ckanapi/cli/paster.py
ckanapi/cli/search.py
ckanapi/cli/utils.py
ckanapi/cli/workers.py
ckanapi/tests/__init__.py
ckanapi/tests/test_call.py
ckanapi/tests/test_cli_action.py
ckanapi/tests/test_cli_dump.py
ckanapi/tests/test_cli_load.py
ckanapi/tests/test_cli_workers.py
ckanapi/tests/test_datapackage.py
ckanapi/tests/test_remote.py
ckanapi/tests/test_testapp.py
ckanapi/tests/mock/mock_ckan.py
ckanapi-4.9.dist-info/licenses/COPYING
ckanapi-4.9.dist-info/licenses/COPYING.fr
ckanapi-4.9.dist-info/METADATA
ckanapi-4.9.dist-info/WHEEL
ckanapi-4.9.dist-info/entry_points.txt
ckanapi-4.9.dist-info/top_level.txt
ckanapi-4.9.dist-info/RECORD
